{
	"json_version": 1,
	"file_name": "512_ND_0008_CF_007.jpg",
	"image_name": "512_ND_0008_CF_007.jpg",
	"image_size": [
		1920,
		1080
	],
	"num_of_object": 3,
	"objects": [
		{
			"class_name": "vehicular_signal",
			"instance_id": 21,
			"data": [
				[
					939.412109375,
					314.208984375
				],
				[
					968.6000000000022,
					324.0
				]
			],
			"attribute": {
				"signal": "red"
			},
			"distance": null,
			"angle": []
		},
		{
			"class_name": "vehicular_signal",
			"instance_id": 23,
			"data": [
				[
					985.46484375,
					319.1396484375
				],
				[
					1012.9000000000015,
					329.40000000000146
				]
			],
			"attribute": {
				"signal": "red"
			},
			"distance": null,
			"angle": []
		},
		{
			"class_name": "vehicular_signal",
			"instance_id": 22,
			"data": [
				[
					1054.439453125,
					309.541015625
				],
				[
					1085.0596679687515,
					320.2959472656257
				]
			],
			"attribute": {
				"signal": "red"
			},
			"distance": null,
			"angle": []
		}
	],
	"flags": {
		"v1": "none",
		"v2": "none"
	}
}